cronyx_client/__init__.py
cronyx_client/cronyx_client.py
cronyx_client/error.py
cronyx_client/job.py
cronyx_client/job_client.py
cronyx_client/job_runner.py
cronyx_client/options.py
cronyx_client/schema.py
cronyx_client/util.py
cronyx_client-1.0.0.dist-info/LICENSE
cronyx_client-1.0.0.dist-info/METADATA
cronyx_client-1.0.0.dist-info/WHEEL
cronyx_client-1.0.0.dist-info/RECORD
