Metadata-Version: 2.1
Name: cronyx-client
Version: 1.0.0
Summary: A Python HTTP client wrapper for CronyxServer, seamlessly integrating the power of Cronyx across platforms using a familiar API interface.
Home-page: https://github.com/yujiosaka/CronyxClient.py
License: MIT
Author: yujiosaka
Author-email: yujisobe@gmail.com
Requires-Python: >=3.8.1,<4.2
Classifier: Development Status :: 3 - Alpha
Classifier: Intended Audience :: Developers
Classifier: License :: OSI Approved :: GNU General Public License v3 (GPLv3)
Classifier: License :: OSI Approved :: MIT License
Classifier: Operating System :: OS Independent
Classifier: Programming Language :: Python :: 3
Classifier: Programming Language :: Python :: 3.9
Classifier: Programming Language :: Python :: 3.10
Classifier: Programming Language :: Python :: 3.11
Classifier: Programming Language :: Python :: 3.12
Requires-Dist: httpx (>=0.25.0,<0.26.0)
Requires-Dist: pydantic (>=2.4.2,<3.0.0)
Project-URL: Repository, https://github.com/yujiosaka/CronyxClient.py
